dlhpcstarter/__init__.py
dlhpcstarter/__main__.py
dlhpcstarter/cluster.py
dlhpcstarter/command_line_arguments.py
dlhpcstarter/trainer.py
dlhpcstarter/utils.py
dlhpcstarter-0.1.8.dist-info/LICENSE
dlhpcstarter-0.1.8.dist-info/METADATA
dlhpcstarter-0.1.8.dist-info/WHEEL
dlhpcstarter-0.1.8.dist-info/entry_points.txt
dlhpcstarter-0.1.8.dist-info/top_level.txt
dlhpcstarter-0.1.8.dist-info/RECORD
