Metadata-Version: 2.1
Name: dlhpcstarter
Version: 0.1.8
Summary: Deep Learning and HPC Starter Pack
Home-page: https://github.com/csiro-mlai/dl_hpc_starter_pack
Author: CSIRO
License: Apache License 2.0
Requires-Python: >=3.7
License-File: LICENSE
Requires-Dist: Bottleneck >=1.3.7
Requires-Dist: hydra-core >=1.3.2
Requires-Dist: lightning >=2.0.1
Requires-Dist: munch >=4.0.0
Requires-Dist: neptune
Requires-Dist: rich >=13.3.2
Requires-Dist: tensorboard >=2.12.0
Requires-Dist: torch >=1.13.1
Requires-Dist: torchmetrics >=0.11.4
Provides-Extra: test
Requires-Dist: pytest ; extra == 'test'
